{
    "settings": {
        "base_url": "",
        "google_analytics_id": "",
        "google_adsense_id": "",
        "google_search_console_verify": "",
        "social_media": {
            "facebook": "",
            "twitter": "",
            "linkedin": "",
            "instagram": ""
        },
        "enable_rtl": false,
        "enable_amp": false,
        "language_code": "en",
        "related_posts_text": "Related Posts",
        "related_posts_position": 1,
        "image_pool_url": "",
        "ai_topic_list": "",
        "content_regex": "",
        "template_folder": "",
        "remove_html_extension": false,
        "font_heading_family": "Arial",
        "font_heading_size": 16,
        "font_heading_color": "#333333",
        "font_body_family": "Arial",
        "font_body_size": 12,
        "font_body_color": "#555555",
        "font_link_family": "Arial",
        "font_link_size": 12,
        "font_link_color": "#007bff"
    },
    "posts": [],
    "pages": [],
    "categories": [],
    "header_menu": [],
    "footer_menu": []
}